{
  "manifestVersion": "3.2",
  "admin": {
    "address": "0x031Da399397987aC26a493151Fd1E6292fb9CC1A",
    "txHash": "0x859cb672231efaf1e8a628f5fa55c66660acab4b29da2c900a256ac2a5ecda01"
  },
  "proxies": [
    {
      "address": "0xe85e685c692f5242E0B4647895206518a3cdCCed",
      "txHash": "0xf6f2f0e2851bfc0b8be9a65251051c667fe39788ed8f2f9c2b9efa027f099783",
      "kind": "transparent"
    },
    {
      "address": "0x954149a56f084e8451401dceFd0242182EB9954c",
      "txHash": "0xe1b5caaef97a9742560e2f56fb4a4043a66be93a2f59c79a29d039fe7e3537b1",
      "kind": "transparent"
    },
    {
      "address": "0xfcC17f498D87Dd77448bb6e4fD35BD7F15C88f9E",
      "txHash": "0x7856e948a4732042237e891af9fb25046d56ad98a4d14812d54fdda3d5c977e6",
      "kind": "transparent"
    },
    {
      "address": "0x0d9ed97aaD16FC7A748B749423384EA091260f44",
      "txHash": "0x9190b37ce01dfa797c8a2d2fcf8229a2ceee0a26232e673e6f5ba61a1e326fb8",
      "kind": "transparent"
    },
    {
      "address": "0x0f38Dd0D6D67388aF2575736629c5F8a9D81C8aA",
      "txHash": "0x73d302f92f6060350c9a4518bf090078ec6fd8750375e1c82b237a3b6238a79d",
      "kind": "transparent"
    },
    {
      "address": "0x4bBd92c96a84A6C0BaDa3a5E6d4e5F86F5AE7951",
      "txHash": "0x4ffe1b0fd13fc9c7c0f0d59e4f2ed955860c38f361ba50b00af268682ca24478",
      "kind": "transparent"
    },
    {
      "address": "0xd7A93d773db5Bd7523dC82BF26B15f16F1E7A341",
      "txHash": "0x5cc8796ccd3c8fbe557380db9a4203f93c50fc4b49c34a7d896fea74f9adf4b0",
      "kind": "transparent"
    },
    {
      "address": "0x2B842D085D9fd62102B7a37Ba717DFa0f2E612f3",
      "txHash": "0x18b8ec9898a720c6fbc43d9982ed6434e450c6817dfa5f63bc62b312dbaac358",
      "kind": "transparent"
    },
    {
      "address": "0xB6b8c02b6Fe4e1EBc9FeEef2C395832aB54688Db",
      "txHash": "0xcd900105ff4c38f41733803471099de3a81009f5ec953baf3bebbc4eb5cc37c0",
      "kind": "transparent"
    },
    {
      "address": "0x9d8124042e8B86B4682B51EBbfB93D17CAab8D2B",
      "txHash": "0xb984c6a4fe7a75706285a55fe978ddcb826e9c573a44d33820e89c3a1c28b516",
      "kind": "transparent"
    }
  ],
  "impls": {
    "c3d5205fbc4412cc2576c46eb246dd1ceebe579561c0a624d737398277f7a344": {
      "address": "0x60f7B32cB824164345f7Bea1D1f43015fF809efe",
      "txHash": "0x4679763465fd79aa09259833e8cab070bb899857de354ea33caf4599ff904e1c",
      "layout": {
        "solcVersion": "0.8.7",
        "storage": [
          {
            "label": "_initialized",
            "offset": 0,
            "slot": "0",
            "type": "t_uint8",
            "contract": "Initializable",
            "src": "@openzeppelin/contracts-upgradeable/proxy/utils/Initializable.sol:62",
            "retypedFrom": "bool"
          },
          {
            "label": "_initializing",
            "offset": 1,
            "slot": "0",
            "type": "t_bool",
            "contract": "Initializable",
            "src": "@openzeppelin/contracts-upgradeable/proxy/utils/Initializable.sol:67"
          },
          {
            "label": "__gap",
            "offset": 0,
            "slot": "1",
            "type": "t_array(t_uint256)50_storage",
            "contract": "ContextUpgradeable",
            "src": "@openzeppelin/contracts-upgradeable/utils/ContextUpgradeable.sol:36"
          },
          {
            "label": "__gap",
            "offset": 0,
            "slot": "51",
            "type": "t_array(t_uint256)50_storage",
            "contract": "ERC165Upgradeable",
            "src": "@openzeppelin/contracts-upgradeable/utils/introspection/ERC165Upgradeable.sol:41"
          },
          {
            "label": "_roles",
            "offset": 0,
            "slot": "101",
            "type": "t_mapping(t_bytes32,t_struct(RoleData)34_storage)",
            "contract": "AccessControlUpgradeable",
            "src": "@openzeppelin/contracts-upgradeable/access/AccessControlUpgradeable.sol:61"
          },
          {
            "label": "__gap",
            "offset": 0,
            "slot": "102",
            "type": "t_array(t_uint256)49_storage",
            "contract": "AccessControlUpgradeable",
            "src": "@openzeppelin/contracts-upgradeable/access/AccessControlUpgradeable.sol:259"
          },
          {
            "label": "_whitelistedCurrencies",
            "offset": 0,
            "slot": "151",
            "type": "t_struct(AddressSet)2325_storage",
            "contract": "CurrencyManager",
            "src": "contracts/CurrencyManager.sol:21"
          }
        ],
        "types": {
          "t_address": {
            "label": "address",
            "numberOfBytes": "20"
          },
          "t_array(t_bytes32)dyn_storage": {
            "label": "bytes32[]",
            "numberOfBytes": "32"
          },
          "t_array(t_uint256)49_storage": {
            "label": "uint256[49]",
            "numberOfBytes": "1568"
          },
          "t_array(t_uint256)50_storage": {
            "label": "uint256[50]",
            "numberOfBytes": "1600"
          },
          "t_bool": {
            "label": "bool",
            "numberOfBytes": "1"
          },
          "t_bytes32": {
            "label": "bytes32",
            "numberOfBytes": "32"
          },
          "t_mapping(t_address,t_bool)": {
            "label": "mapping(address => bool)",
            "numberOfBytes": "32"
          },
          "t_mapping(t_bytes32,t_struct(RoleData)34_storage)": {
            "label": "mapping(bytes32 => struct AccessControlUpgradeable.RoleData)",
            "numberOfBytes": "32"
          },
          "t_mapping(t_bytes32,t_uint256)": {
            "label": "mapping(bytes32 => uint256)",
            "numberOfBytes": "32"
          },
          "t_struct(AddressSet)2325_storage": {
            "label": "struct EnumerableSetUpgradeable.AddressSet",
            "members": [
              {
                "label": "_inner",
                "type": "t_struct(Set)2010_storage",
                "offset": 0,
                "slot": "0"
              }
            ],
            "numberOfBytes": "64"
          },
          "t_struct(RoleData)34_storage": {
            "label": "struct AccessControlUpgradeable.RoleData",
            "members": [
              {
                "label": "members",
                "type": "t_mapping(t_address,t_bool)",
                "offset": 0,
                "slot": "0"
              },
              {
                "label": "adminRole",
                "type": "t_bytes32",
                "offset": 0,
                "slot": "1"
              }
            ],
            "numberOfBytes": "64"
          },
          "t_struct(Set)2010_storage": {
            "label": "struct EnumerableSetUpgradeable.Set",
            "members": [
              {
                "label": "_values",
                "type": "t_array(t_bytes32)dyn_storage",
                "offset": 0,
                "slot": "0"
              },
              {
                "label": "_indexes",
                "type": "t_mapping(t_bytes32,t_uint256)",
                "offset": 0,
                "slot": "1"
              }
            ],
            "numberOfBytes": "64"
          },
          "t_uint256": {
            "label": "uint256",
            "numberOfBytes": "32"
          },
          "t_uint8": {
            "label": "uint8",
            "numberOfBytes": "1"
          }
        }
      }
    },
    "1926fadfc8f94fde0b4ce951d0d17a20eaa5b6f3fd76443b55826d22468d46bd": {
      "address": "0xB7CC88762c6E7fbc32824Ba8f458B7F7eECA75E9",
      "txHash": "0xf28d3416808302b4a5aa55a61a799f41cb1a4e458f8f3d724b14f4a509698e94",
      "layout": {
        "solcVersion": "0.8.7",
        "storage": [
          {
            "label": "_initialized",
            "offset": 0,
            "slot": "0",
            "type": "t_uint8",
            "contract": "Initializable",
            "src": "@openzeppelin/contracts-upgradeable/proxy/utils/Initializable.sol:62",
            "retypedFrom": "bool"
          },
          {
            "label": "_initializing",
            "offset": 1,
            "slot": "0",
            "type": "t_bool",
            "contract": "Initializable",
            "src": "@openzeppelin/contracts-upgradeable/proxy/utils/Initializable.sol:67"
          },
          {
            "label": "__gap",
            "offset": 0,
            "slot": "1",
            "type": "t_array(t_uint256)50_storage",
            "contract": "ContextUpgradeable",
            "src": "@openzeppelin/contracts-upgradeable/utils/ContextUpgradeable.sol:36"
          },
          {
            "label": "__gap",
            "offset": 0,
            "slot": "51",
            "type": "t_array(t_uint256)50_storage",
            "contract": "ERC165Upgradeable",
            "src": "@openzeppelin/contracts-upgradeable/utils/introspection/ERC165Upgradeable.sol:41"
          },
          {
            "label": "_roles",
            "offset": 0,
            "slot": "101",
            "type": "t_mapping(t_bytes32,t_struct(RoleData)34_storage)",
            "contract": "AccessControlUpgradeable",
            "src": "@openzeppelin/contracts-upgradeable/access/AccessControlUpgradeable.sol:61"
          },
          {
            "label": "__gap",
            "offset": 0,
            "slot": "102",
            "type": "t_array(t_uint256)49_storage",
            "contract": "AccessControlUpgradeable",
            "src": "@openzeppelin/contracts-upgradeable/access/AccessControlUpgradeable.sol:259"
          },
          {
            "label": "_whitelistedStrategies",
            "offset": 0,
            "slot": "151",
            "type": "t_struct(AddressSet)2398_storage",
            "contract": "ExecutionManager",
            "src": "contracts/ExecutionManager.sol:21"
          }
        ],
        "types": {
          "t_address": {
            "label": "address",
            "numberOfBytes": "20"
          },
          "t_array(t_bytes32)dyn_storage": {
            "label": "bytes32[]",
            "numberOfBytes": "32"
          },
          "t_array(t_uint256)49_storage": {
            "label": "uint256[49]",
            "numberOfBytes": "1568"
          },
          "t_array(t_uint256)50_storage": {
            "label": "uint256[50]",
            "numberOfBytes": "1600"
          },
          "t_bool": {
            "label": "bool",
            "numberOfBytes": "1"
          },
          "t_bytes32": {
            "label": "bytes32",
            "numberOfBytes": "32"
          },
          "t_mapping(t_address,t_bool)": {
            "label": "mapping(address => bool)",
            "numberOfBytes": "32"
          },
          "t_mapping(t_bytes32,t_struct(RoleData)34_storage)": {
            "label": "mapping(bytes32 => struct AccessControlUpgradeable.RoleData)",
            "numberOfBytes": "32"
          },
          "t_mapping(t_bytes32,t_uint256)": {
            "label": "mapping(bytes32 => uint256)",
            "numberOfBytes": "32"
          },
          "t_struct(AddressSet)2398_storage": {
            "label": "struct EnumerableSetUpgradeable.AddressSet",
            "members": [
              {
                "label": "_inner",
                "type": "t_struct(Set)2083_storage",
                "offset": 0,
                "slot": "0"
              }
            ],
            "numberOfBytes": "64"
          },
          "t_struct(RoleData)34_storage": {
            "label": "struct AccessControlUpgradeable.RoleData",
            "members": [
              {
                "label": "members",
                "type": "t_mapping(t_address,t_bool)",
                "offset": 0,
                "slot": "0"
              },
              {
                "label": "adminRole",
                "type": "t_bytes32",
                "offset": 0,
                "slot": "1"
              }
            ],
            "numberOfBytes": "64"
          },
          "t_struct(Set)2083_storage": {
            "label": "struct EnumerableSetUpgradeable.Set",
            "members": [
              {
                "label": "_values",
                "type": "t_array(t_bytes32)dyn_storage",
                "offset": 0,
                "slot": "0"
              },
              {
                "label": "_indexes",
                "type": "t_mapping(t_bytes32,t_uint256)",
                "offset": 0,
                "slot": "1"
              }
            ],
            "numberOfBytes": "64"
          },
          "t_uint256": {
            "label": "uint256",
            "numberOfBytes": "32"
          },
          "t_uint8": {
            "label": "uint8",
            "numberOfBytes": "1"
          }
        }
      }
    },
    "8a0f0ec4ba34d3d8e1752702306c778ee17b36a801c2e0dadfcdba7c7eaef863": {
      "address": "0x320b6996a815AF9C4A773fD59A3130994a8daC2b",
      "txHash": "0x653b51c4c02d5262357c54cb782af9c54ee6c744912fca3071cf4cb98f91b699",
      "layout": {
        "solcVersion": "0.8.7",
        "storage": [
          {
            "label": "_initialized",
            "offset": 0,
            "slot": "0",
            "type": "t_uint8",
            "contract": "Initializable",
            "src": "@openzeppelin/contracts-upgradeable/proxy/utils/Initializable.sol:62",
            "retypedFrom": "bool"
          },
          {
            "label": "_initializing",
            "offset": 1,
            "slot": "0",
            "type": "t_bool",
            "contract": "Initializable",
            "src": "@openzeppelin/contracts-upgradeable/proxy/utils/Initializable.sol:67"
          },
          {
            "label": "__gap",
            "offset": 0,
            "slot": "1",
            "type": "t_array(t_uint256)50_storage",
            "contract": "ContextUpgradeable",
            "src": "@openzeppelin/contracts-upgradeable/utils/ContextUpgradeable.sol:36"
          },
          {
            "label": "__gap",
            "offset": 0,
            "slot": "51",
            "type": "t_array(t_uint256)50_storage",
            "contract": "ERC165Upgradeable",
            "src": "@openzeppelin/contracts-upgradeable/utils/introspection/ERC165Upgradeable.sol:41"
          },
          {
            "label": "_roles",
            "offset": 0,
            "slot": "101",
            "type": "t_mapping(t_bytes32,t_struct(RoleData)34_storage)",
            "contract": "AccessControlUpgradeable",
            "src": "@openzeppelin/contracts-upgradeable/access/AccessControlUpgradeable.sol:61"
          },
          {
            "label": "__gap",
            "offset": 0,
            "slot": "102",
            "type": "t_array(t_uint256)49_storage",
            "contract": "AccessControlUpgradeable",
            "src": "@openzeppelin/contracts-upgradeable/access/AccessControlUpgradeable.sol:259"
          },
          {
            "label": "royaltyFeeLimit",
            "offset": 0,
            "slot": "151",
            "type": "t_uint256",
            "contract": "RoyaltyFeeRegistry",
            "src": "contracts/royaltyFeeHelpers/RoyaltyFeeRegistry.sol:27"
          },
          {
            "label": "_royaltyFeeInfoCollection",
            "offset": 0,
            "slot": "152",
            "type": "t_mapping(t_address,t_struct(FeeInfo)14450_storage)",
            "contract": "RoyaltyFeeRegistry",
            "src": "contracts/royaltyFeeHelpers/RoyaltyFeeRegistry.sol:29"
          }
        ],
        "types": {
          "t_address": {
            "label": "address",
            "numberOfBytes": "20"
          },
          "t_array(t_uint256)49_storage": {
            "label": "uint256[49]",
            "numberOfBytes": "1568"
          },
          "t_array(t_uint256)50_storage": {
            "label": "uint256[50]",
            "numberOfBytes": "1600"
          },
          "t_bool": {
            "label": "bool",
            "numberOfBytes": "1"
          },
          "t_bytes32": {
            "label": "bytes32",
            "numberOfBytes": "32"
          },
          "t_mapping(t_address,t_bool)": {
            "label": "mapping(address => bool)",
            "numberOfBytes": "32"
          },
          "t_mapping(t_address,t_struct(FeeInfo)14450_storage)": {
            "label": "mapping(address => struct RoyaltyFeeRegistry.FeeInfo)",
            "numberOfBytes": "32"
          },
          "t_mapping(t_bytes32,t_struct(RoleData)34_storage)": {
            "label": "mapping(bytes32 => struct AccessControlUpgradeable.RoleData)",
            "numberOfBytes": "32"
          },
          "t_struct(FeeInfo)14450_storage": {
            "label": "struct RoyaltyFeeRegistry.FeeInfo",
            "members": [
              {
                "label": "setter",
                "type": "t_address",
                "offset": 0,
                "slot": "0"
              },
              {
                "label": "receiver",
                "type": "t_address",
                "offset": 0,
                "slot": "1"
              },
              {
                "label": "fee",
                "type": "t_uint256",
                "offset": 0,
                "slot": "2"
              }
            ],
            "numberOfBytes": "96"
          },
          "t_struct(RoleData)34_storage": {
            "label": "struct AccessControlUpgradeable.RoleData",
            "members": [
              {
                "label": "members",
                "type": "t_mapping(t_address,t_bool)",
                "offset": 0,
                "slot": "0"
              },
              {
                "label": "adminRole",
                "type": "t_bytes32",
                "offset": 0,
                "slot": "1"
              }
            ],
            "numberOfBytes": "64"
          },
          "t_uint256": {
            "label": "uint256",
            "numberOfBytes": "32"
          },
          "t_uint8": {
            "label": "uint8",
            "numberOfBytes": "1"
          }
        }
      }
    },
    "de83b9a52b90c07079f58115b7d84ca3c631d4d0ba2abbe211bea402a9113584": {
      "address": "0x619F1DAFE1eDAf43a2f5d9CF402a15d256495493",
      "txHash": "0xffb73aa3b705dda2d4743fed943580ba94c47dadf0dc1be7bc6ece63693bef08",
      "layout": {
        "solcVersion": "0.8.7",
        "storage": [
          {
            "label": "_initialized",
            "offset": 0,
            "slot": "0",
            "type": "t_uint8",
            "contract": "Initializable",
            "src": "@openzeppelin/contracts-upgradeable/proxy/utils/Initializable.sol:62",
            "retypedFrom": "bool"
          },
          {
            "label": "_initializing",
            "offset": 1,
            "slot": "0",
            "type": "t_bool",
            "contract": "Initializable",
            "src": "@openzeppelin/contracts-upgradeable/proxy/utils/Initializable.sol:67"
          },
          {
            "label": "__gap",
            "offset": 0,
            "slot": "1",
            "type": "t_array(t_uint256)50_storage",
            "contract": "ContextUpgradeable",
            "src": "@openzeppelin/contracts-upgradeable/utils/ContextUpgradeable.sol:36"
          },
          {
            "label": "__gap",
            "offset": 0,
            "slot": "51",
            "type": "t_array(t_uint256)50_storage",
            "contract": "ERC165Upgradeable",
            "src": "@openzeppelin/contracts-upgradeable/utils/introspection/ERC165Upgradeable.sol:41"
          },
          {
            "label": "_roles",
            "offset": 0,
            "slot": "101",
            "type": "t_mapping(t_bytes32,t_struct(RoleData)34_storage)",
            "contract": "AccessControlUpgradeable",
            "src": "@openzeppelin/contracts-upgradeable/access/AccessControlUpgradeable.sol:61"
          },
          {
            "label": "__gap",
            "offset": 0,
            "slot": "102",
            "type": "t_array(t_uint256)49_storage",
            "contract": "AccessControlUpgradeable",
            "src": "@openzeppelin/contracts-upgradeable/access/AccessControlUpgradeable.sol:259"
          },
          {
            "label": "royaltyFeeRegistry",
            "offset": 0,
            "slot": "151",
            "type": "t_contract(IRoyaltyFeeRegistry)12815",
            "contract": "RoyaltyFeeManager",
            "src": "contracts/RoyaltyFeeManager.sol:23"
          }
        ],
        "types": {
          "t_address": {
            "label": "address",
            "numberOfBytes": "20"
          },
          "t_array(t_uint256)49_storage": {
            "label": "uint256[49]",
            "numberOfBytes": "1568"
          },
          "t_array(t_uint256)50_storage": {
            "label": "uint256[50]",
            "numberOfBytes": "1600"
          },
          "t_bool": {
            "label": "bool",
            "numberOfBytes": "1"
          },
          "t_bytes32": {
            "label": "bytes32",
            "numberOfBytes": "32"
          },
          "t_contract(IRoyaltyFeeRegistry)12815": {
            "label": "contract IRoyaltyFeeRegistry",
            "numberOfBytes": "20"
          },
          "t_mapping(t_address,t_bool)": {
            "label": "mapping(address => bool)",
            "numberOfBytes": "32"
          },
          "t_mapping(t_bytes32,t_struct(RoleData)34_storage)": {
            "label": "mapping(bytes32 => struct AccessControlUpgradeable.RoleData)",
            "numberOfBytes": "32"
          },
          "t_struct(RoleData)34_storage": {
            "label": "struct AccessControlUpgradeable.RoleData",
            "members": [
              {
                "label": "members",
                "type": "t_mapping(t_address,t_bool)",
                "offset": 0,
                "slot": "0"
              },
              {
                "label": "adminRole",
                "type": "t_bytes32",
                "offset": 0,
                "slot": "1"
              }
            ],
            "numberOfBytes": "64"
          },
          "t_uint256": {
            "label": "uint256",
            "numberOfBytes": "32"
          },
          "t_uint8": {
            "label": "uint8",
            "numberOfBytes": "1"
          }
        }
      }
    },
    "79a277dd0e119b906875c59ff34baf2a469e5f2482e6ed9d5dccc42086d33059": {
      "address": "0xd047e208b9A3feDD27ED361586C9827C91c0093d",
      "txHash": "0x03e4bede1ef3e254ff0c6dfc6507fe9e928e3843d296c164f4c557ffe8bd4ede",
      "layout": {
        "solcVersion": "0.8.7",
        "storage": [
          {
            "label": "_initialized",
            "offset": 0,
            "slot": "0",
            "type": "t_uint8",
            "contract": "Initializable",
            "src": "@openzeppelin/contracts-upgradeable/proxy/utils/Initializable.sol:62",
            "retypedFrom": "bool"
          },
          {
            "label": "_initializing",
            "offset": 1,
            "slot": "0",
            "type": "t_bool",
            "contract": "Initializable",
            "src": "@openzeppelin/contracts-upgradeable/proxy/utils/Initializable.sol:67"
          },
          {
            "label": "__gap",
            "offset": 0,
            "slot": "1",
            "type": "t_array(t_uint256)50_storage",
            "contract": "ContextUpgradeable",
            "src": "@openzeppelin/contracts-upgradeable/utils/ContextUpgradeable.sol:36"
          },
          {
            "label": "__gap",
            "offset": 0,
            "slot": "51",
            "type": "t_array(t_uint256)50_storage",
            "contract": "ERC165Upgradeable",
            "src": "@openzeppelin/contracts-upgradeable/utils/introspection/ERC165Upgradeable.sol:41"
          },
          {
            "label": "_roles",
            "offset": 0,
            "slot": "101",
            "type": "t_mapping(t_bytes32,t_struct(RoleData)34_storage)",
            "contract": "AccessControlUpgradeable",
            "src": "@openzeppelin/contracts-upgradeable/access/AccessControlUpgradeable.sol:61"
          },
          {
            "label": "__gap",
            "offset": 0,
            "slot": "102",
            "type": "t_array(t_uint256)49_storage",
            "contract": "AccessControlUpgradeable",
            "src": "@openzeppelin/contracts-upgradeable/access/AccessControlUpgradeable.sol:259"
          },
          {
            "label": "_status",
            "offset": 0,
            "slot": "151",
            "type": "t_uint256",
            "contract": "ReentrancyGuardUpgradeable",
            "src": "@openzeppelin/contracts-upgradeable/security/ReentrancyGuardUpgradeable.sol:38"
          },
          {
            "label": "__gap",
            "offset": 0,
            "slot": "152",
            "type": "t_array(t_uint256)49_storage",
            "contract": "ReentrancyGuardUpgradeable",
            "src": "@openzeppelin/contracts-upgradeable/security/ReentrancyGuardUpgradeable.sol:80"
          },
          {
            "label": "WETH",
            "offset": 0,
            "slot": "201",
            "type": "t_address",
            "contract": "DareMarket",
            "src": "contracts/DareMarket.sol:50"
          },
          {
            "label": "DOMAIN_SEPARATOR",
            "offset": 0,
            "slot": "202",
            "type": "t_bytes32",
            "contract": "DareMarket",
            "src": "contracts/DareMarket.sol:51"
          },
          {
            "label": "protocolFeeRecipient",
            "offset": 0,
            "slot": "203",
            "type": "t_address",
            "contract": "DareMarket",
            "src": "contracts/DareMarket.sol:53"
          },
          {
            "label": "currencyManager",
            "offset": 0,
            "slot": "204",
            "type": "t_contract(ICurrencyManager)4728",
            "contract": "DareMarket",
            "src": "contracts/DareMarket.sol:55"
          },
          {
            "label": "executionManager",
            "offset": 0,
            "slot": "205",
            "type": "t_contract(IExecutionManager)4797",
            "contract": "DareMarket",
            "src": "contracts/DareMarket.sol:56"
          },
          {
            "label": "royaltyFeeManager",
            "offset": 0,
            "slot": "206",
            "type": "t_contract(IRoyaltyFeeManager)4853",
            "contract": "DareMarket",
            "src": "contracts/DareMarket.sol:57"
          },
          {
            "label": "transferSelectorNFT",
            "offset": 0,
            "slot": "207",
            "type": "t_contract(ITransferSelectorNFT)4879",
            "contract": "DareMarket",
            "src": "contracts/DareMarket.sol:58"
          },
          {
            "label": "userMinOrderNonce",
            "offset": 0,
            "slot": "208",
            "type": "t_mapping(t_address,t_uint256)",
            "contract": "DareMarket",
            "src": "contracts/DareMarket.sol:60"
          },
          {
            "label": "_isUserOrderNonceExecutedOrCancelled",
            "offset": 0,
            "slot": "209",
            "type": "t_mapping(t_address,t_mapping(t_uint256,t_bool))",
            "contract": "DareMarket",
            "src": "contracts/DareMarket.sol:61"
          }
        ],
        "types": {
          "t_address": {
            "label": "address",
            "numberOfBytes": "20"
          },
          "t_array(t_uint256)49_storage": {
            "label": "uint256[49]",
            "numberOfBytes": "1568"
          },
          "t_array(t_uint256)50_storage": {
            "label": "uint256[50]",
            "numberOfBytes": "1600"
          },
          "t_bool": {
            "label": "bool",
            "numberOfBytes": "1"
          },
          "t_bytes32": {
            "label": "bytes32",
            "numberOfBytes": "32"
          },
          "t_contract(ICurrencyManager)4728": {
            "label": "contract ICurrencyManager",
            "numberOfBytes": "20"
          },
          "t_contract(IExecutionManager)4797": {
            "label": "contract IExecutionManager",
            "numberOfBytes": "20"
          },
          "t_contract(IRoyaltyFeeManager)4853": {
            "label": "contract IRoyaltyFeeManager",
            "numberOfBytes": "20"
          },
          "t_contract(ITransferSelectorNFT)4879": {
            "label": "contract ITransferSelectorNFT",
            "numberOfBytes": "20"
          },
          "t_mapping(t_address,t_bool)": {
            "label": "mapping(address => bool)",
            "numberOfBytes": "32"
          },
          "t_mapping(t_address,t_mapping(t_uint256,t_bool))": {
            "label": "mapping(address => mapping(uint256 => bool))",
            "numberOfBytes": "32"
          },
          "t_mapping(t_address,t_uint256)": {
            "label": "mapping(address => uint256)",
            "numberOfBytes": "32"
          },
          "t_mapping(t_bytes32,t_struct(RoleData)34_storage)": {
            "label": "mapping(bytes32 => struct AccessControlUpgradeable.RoleData)",
            "numberOfBytes": "32"
          },
          "t_mapping(t_uint256,t_bool)": {
            "label": "mapping(uint256 => bool)",
            "numberOfBytes": "32"
          },
          "t_struct(RoleData)34_storage": {
            "label": "struct AccessControlUpgradeable.RoleData",
            "members": [
              {
                "label": "members",
                "type": "t_mapping(t_address,t_bool)",
                "offset": 0,
                "slot": "0"
              },
              {
                "label": "adminRole",
                "type": "t_bytes32",
                "offset": 0,
                "slot": "1"
              }
            ],
            "numberOfBytes": "64"
          },
          "t_uint256": {
            "label": "uint256",
            "numberOfBytes": "32"
          },
          "t_uint8": {
            "label": "uint8",
            "numberOfBytes": "1"
          }
        }
      }
    },
    "aeb405af7a92f604164c172b63d4b08e91d716c540b49af8e327bed551ca6e38": {
      "address": "0x4eE89877330A247065E6E340BB914B3bba304d3e",
      "txHash": "0x634a339e59c8087613ed13bf13884499e4b603aded61116289f65fea61eda11f",
      "layout": {
        "solcVersion": "0.8.7",
        "storage": [
          {
            "label": "_initialized",
            "offset": 0,
            "slot": "0",
            "type": "t_uint8",
            "contract": "Initializable",
            "src": "@openzeppelin/contracts-upgradeable/proxy/utils/Initializable.sol:62",
            "retypedFrom": "bool"
          },
          {
            "label": "_initializing",
            "offset": 1,
            "slot": "0",
            "type": "t_bool",
            "contract": "Initializable",
            "src": "@openzeppelin/contracts-upgradeable/proxy/utils/Initializable.sol:67"
          },
          {
            "label": "__gap",
            "offset": 0,
            "slot": "1",
            "type": "t_array(t_uint256)50_storage",
            "contract": "ContextUpgradeable",
            "src": "@openzeppelin/contracts-upgradeable/utils/ContextUpgradeable.sol:36"
          },
          {
            "label": "__gap",
            "offset": 0,
            "slot": "51",
            "type": "t_array(t_uint256)50_storage",
            "contract": "ERC165Upgradeable",
            "src": "@openzeppelin/contracts-upgradeable/utils/introspection/ERC165Upgradeable.sol:41"
          },
          {
            "label": "_roles",
            "offset": 0,
            "slot": "101",
            "type": "t_mapping(t_bytes32,t_struct(RoleData)34_storage)",
            "contract": "AccessControlUpgradeable",
            "src": "@openzeppelin/contracts-upgradeable/access/AccessControlUpgradeable.sol:61"
          },
          {
            "label": "__gap",
            "offset": 0,
            "slot": "102",
            "type": "t_array(t_uint256)49_storage",
            "contract": "AccessControlUpgradeable",
            "src": "@openzeppelin/contracts-upgradeable/access/AccessControlUpgradeable.sol:259"
          }
        ],
        "types": {
          "t_address": {
            "label": "address",
            "numberOfBytes": "20"
          },
          "t_array(t_uint256)49_storage": {
            "label": "uint256[49]",
            "numberOfBytes": "1568"
          },
          "t_array(t_uint256)50_storage": {
            "label": "uint256[50]",
            "numberOfBytes": "1600"
          },
          "t_bool": {
            "label": "bool",
            "numberOfBytes": "1"
          },
          "t_bytes32": {
            "label": "bytes32",
            "numberOfBytes": "32"
          },
          "t_mapping(t_address,t_bool)": {
            "label": "mapping(address => bool)",
            "numberOfBytes": "32"
          },
          "t_mapping(t_bytes32,t_struct(RoleData)34_storage)": {
            "label": "mapping(bytes32 => struct AccessControlUpgradeable.RoleData)",
            "numberOfBytes": "32"
          },
          "t_struct(RoleData)34_storage": {
            "label": "struct AccessControlUpgradeable.RoleData",
            "members": [
              {
                "label": "members",
                "type": "t_mapping(t_address,t_bool)",
                "offset": 0,
                "slot": "0"
              },
              {
                "label": "adminRole",
                "type": "t_bytes32",
                "offset": 0,
                "slot": "1"
              }
            ],
            "numberOfBytes": "64"
          },
          "t_uint256": {
            "label": "uint256",
            "numberOfBytes": "32"
          },
          "t_uint8": {
            "label": "uint8",
            "numberOfBytes": "1"
          }
        }
      }
    },
    "c6846f131fbdcca9a8f07f844a4af7de3f83b4c4b9bf4190f2f06a0c9e187990": {
      "address": "0x477575Cd78Fe97955b17FfE36f23310d71BB4398",
      "txHash": "0xa8e70bc4c2810b421f99f59a1e3efaba3555d0284d34f83a309c6f951d33a987",
      "layout": {
        "solcVersion": "0.8.7",
        "storage": [
          {
            "label": "_initialized",
            "offset": 0,
            "slot": "0",
            "type": "t_uint8",
            "contract": "Initializable",
            "src": "@openzeppelin/contracts-upgradeable/proxy/utils/Initializable.sol:62",
            "retypedFrom": "bool"
          },
          {
            "label": "_initializing",
            "offset": 1,
            "slot": "0",
            "type": "t_bool",
            "contract": "Initializable",
            "src": "@openzeppelin/contracts-upgradeable/proxy/utils/Initializable.sol:67"
          },
          {
            "label": "__gap",
            "offset": 0,
            "slot": "1",
            "type": "t_array(t_uint256)50_storage",
            "contract": "ContextUpgradeable",
            "src": "@openzeppelin/contracts-upgradeable/utils/ContextUpgradeable.sol:36"
          },
          {
            "label": "__gap",
            "offset": 0,
            "slot": "51",
            "type": "t_array(t_uint256)50_storage",
            "contract": "ERC165Upgradeable",
            "src": "@openzeppelin/contracts-upgradeable/utils/introspection/ERC165Upgradeable.sol:41"
          },
          {
            "label": "_roles",
            "offset": 0,
            "slot": "101",
            "type": "t_mapping(t_bytes32,t_struct(RoleData)34_storage)",
            "contract": "AccessControlUpgradeable",
            "src": "@openzeppelin/contracts-upgradeable/access/AccessControlUpgradeable.sol:61"
          },
          {
            "label": "__gap",
            "offset": 0,
            "slot": "102",
            "type": "t_array(t_uint256)49_storage",
            "contract": "AccessControlUpgradeable",
            "src": "@openzeppelin/contracts-upgradeable/access/AccessControlUpgradeable.sol:259"
          }
        ],
        "types": {
          "t_address": {
            "label": "address",
            "numberOfBytes": "20"
          },
          "t_array(t_uint256)49_storage": {
            "label": "uint256[49]",
            "numberOfBytes": "1568"
          },
          "t_array(t_uint256)50_storage": {
            "label": "uint256[50]",
            "numberOfBytes": "1600"
          },
          "t_bool": {
            "label": "bool",
            "numberOfBytes": "1"
          },
          "t_bytes32": {
            "label": "bytes32",
            "numberOfBytes": "32"
          },
          "t_mapping(t_address,t_bool)": {
            "label": "mapping(address => bool)",
            "numberOfBytes": "32"
          },
          "t_mapping(t_bytes32,t_struct(RoleData)34_storage)": {
            "label": "mapping(bytes32 => struct AccessControlUpgradeable.RoleData)",
            "numberOfBytes": "32"
          },
          "t_struct(RoleData)34_storage": {
            "label": "struct AccessControlUpgradeable.RoleData",
            "members": [
              {
                "label": "members",
                "type": "t_mapping(t_address,t_bool)",
                "offset": 0,
                "slot": "0"
              },
              {
                "label": "adminRole",
                "type": "t_bytes32",
                "offset": 0,
                "slot": "1"
              }
            ],
            "numberOfBytes": "64"
          },
          "t_uint256": {
            "label": "uint256",
            "numberOfBytes": "32"
          },
          "t_uint8": {
            "label": "uint8",
            "numberOfBytes": "1"
          }
        }
      }
    },
    "c5db9b2decf9c6f8a3b9ddcbc60cc530a2dc876c6d2ac471eff1196a0b156256": {
      "address": "0x98ef61E5283b34B5080fdE35A022C79C190787eC",
      "txHash": "0xb501981a77ab8286ea439f18fa3c6057a64a422aab6770dabe703ff93bf342d7",
      "layout": {
        "solcVersion": "0.8.7",
        "storage": [
          {
            "label": "_initialized",
            "offset": 0,
            "slot": "0",
            "type": "t_uint8",
            "contract": "Initializable",
            "src": "@openzeppelin/contracts-upgradeable/proxy/utils/Initializable.sol:62",
            "retypedFrom": "bool"
          },
          {
            "label": "_initializing",
            "offset": 1,
            "slot": "0",
            "type": "t_bool",
            "contract": "Initializable",
            "src": "@openzeppelin/contracts-upgradeable/proxy/utils/Initializable.sol:67"
          },
          {
            "label": "__gap",
            "offset": 0,
            "slot": "1",
            "type": "t_array(t_uint256)50_storage",
            "contract": "ContextUpgradeable",
            "src": "@openzeppelin/contracts-upgradeable/utils/ContextUpgradeable.sol:36"
          },
          {
            "label": "__gap",
            "offset": 0,
            "slot": "51",
            "type": "t_array(t_uint256)50_storage",
            "contract": "ERC165Upgradeable",
            "src": "@openzeppelin/contracts-upgradeable/utils/introspection/ERC165Upgradeable.sol:41"
          },
          {
            "label": "_roles",
            "offset": 0,
            "slot": "101",
            "type": "t_mapping(t_bytes32,t_struct(RoleData)34_storage)",
            "contract": "AccessControlUpgradeable",
            "src": "@openzeppelin/contracts-upgradeable/access/AccessControlUpgradeable.sol:61"
          },
          {
            "label": "__gap",
            "offset": 0,
            "slot": "102",
            "type": "t_array(t_uint256)49_storage",
            "contract": "AccessControlUpgradeable",
            "src": "@openzeppelin/contracts-upgradeable/access/AccessControlUpgradeable.sol:259"
          }
        ],
        "types": {
          "t_address": {
            "label": "address",
            "numberOfBytes": "20"
          },
          "t_array(t_uint256)49_storage": {
            "label": "uint256[49]",
            "numberOfBytes": "1568"
          },
          "t_array(t_uint256)50_storage": {
            "label": "uint256[50]",
            "numberOfBytes": "1600"
          },
          "t_bool": {
            "label": "bool",
            "numberOfBytes": "1"
          },
          "t_bytes32": {
            "label": "bytes32",
            "numberOfBytes": "32"
          },
          "t_mapping(t_address,t_bool)": {
            "label": "mapping(address => bool)",
            "numberOfBytes": "32"
          },
          "t_mapping(t_bytes32,t_struct(RoleData)34_storage)": {
            "label": "mapping(bytes32 => struct AccessControlUpgradeable.RoleData)",
            "numberOfBytes": "32"
          },
          "t_struct(RoleData)34_storage": {
            "label": "struct AccessControlUpgradeable.RoleData",
            "members": [
              {
                "label": "members",
                "type": "t_mapping(t_address,t_bool)",
                "offset": 0,
                "slot": "0"
              },
              {
                "label": "adminRole",
                "type": "t_bytes32",
                "offset": 0,
                "slot": "1"
              }
            ],
            "numberOfBytes": "64"
          },
          "t_uint256": {
            "label": "uint256",
            "numberOfBytes": "32"
          },
          "t_uint8": {
            "label": "uint8",
            "numberOfBytes": "1"
          }
        }
      }
    },
    "15113b6befa2f663fc599e63bf2b6d5a402f9134ed25cea7f76742fde625e23f": {
      "address": "0x4289244c3d2671b1cb5Af0BDa54c794DD5785f07",
      "txHash": "0x590e2a3908197d89bd8466ae6ecde38e46245197e92b5fce7e02667705521230",
      "layout": {
        "solcVersion": "0.8.7",
        "storage": [
          {
            "label": "_initialized",
            "offset": 0,
            "slot": "0",
            "type": "t_uint8",
            "contract": "Initializable",
            "src": "@openzeppelin/contracts-upgradeable/proxy/utils/Initializable.sol:62",
            "retypedFrom": "bool"
          },
          {
            "label": "_initializing",
            "offset": 1,
            "slot": "0",
            "type": "t_bool",
            "contract": "Initializable",
            "src": "@openzeppelin/contracts-upgradeable/proxy/utils/Initializable.sol:67"
          },
          {
            "label": "__gap",
            "offset": 0,
            "slot": "1",
            "type": "t_array(t_uint256)50_storage",
            "contract": "ContextUpgradeable",
            "src": "@openzeppelin/contracts-upgradeable/utils/ContextUpgradeable.sol:36"
          },
          {
            "label": "__gap",
            "offset": 0,
            "slot": "51",
            "type": "t_array(t_uint256)50_storage",
            "contract": "ERC165Upgradeable",
            "src": "@openzeppelin/contracts-upgradeable/utils/introspection/ERC165Upgradeable.sol:41"
          },
          {
            "label": "_roles",
            "offset": 0,
            "slot": "101",
            "type": "t_mapping(t_bytes32,t_struct(RoleData)34_storage)",
            "contract": "AccessControlUpgradeable",
            "src": "@openzeppelin/contracts-upgradeable/access/AccessControlUpgradeable.sol:61"
          },
          {
            "label": "__gap",
            "offset": 0,
            "slot": "102",
            "type": "t_array(t_uint256)49_storage",
            "contract": "AccessControlUpgradeable",
            "src": "@openzeppelin/contracts-upgradeable/access/AccessControlUpgradeable.sol:259"
          },
          {
            "label": "TRANSFER_MANAGER_ERC721",
            "offset": 0,
            "slot": "151",
            "type": "t_address",
            "contract": "TransferSelectorNFT",
            "src": "contracts/TransferSelectorNFT.sol:25"
          },
          {
            "label": "TRANSFER_MANAGER_ERC1155",
            "offset": 0,
            "slot": "152",
            "type": "t_address",
            "contract": "TransferSelectorNFT",
            "src": "contracts/TransferSelectorNFT.sol:28"
          },
          {
            "label": "transferManagerSelectorForCollection",
            "offset": 0,
            "slot": "153",
            "type": "t_mapping(t_address,t_address)",
            "contract": "TransferSelectorNFT",
            "src": "contracts/TransferSelectorNFT.sol:31"
          }
        ],
        "types": {
          "t_address": {
            "label": "address",
            "numberOfBytes": "20"
          },
          "t_array(t_uint256)49_storage": {
            "label": "uint256[49]",
            "numberOfBytes": "1568"
          },
          "t_array(t_uint256)50_storage": {
            "label": "uint256[50]",
            "numberOfBytes": "1600"
          },
          "t_bool": {
            "label": "bool",
            "numberOfBytes": "1"
          },
          "t_bytes32": {
            "label": "bytes32",
            "numberOfBytes": "32"
          },
          "t_mapping(t_address,t_address)": {
            "label": "mapping(address => address)",
            "numberOfBytes": "32"
          },
          "t_mapping(t_address,t_bool)": {
            "label": "mapping(address => bool)",
            "numberOfBytes": "32"
          },
          "t_mapping(t_bytes32,t_struct(RoleData)34_storage)": {
            "label": "mapping(bytes32 => struct AccessControlUpgradeable.RoleData)",
            "numberOfBytes": "32"
          },
          "t_struct(RoleData)34_storage": {
            "label": "struct AccessControlUpgradeable.RoleData",
            "members": [
              {
                "label": "members",
                "type": "t_mapping(t_address,t_bool)",
                "offset": 0,
                "slot": "0"
              },
              {
                "label": "adminRole",
                "type": "t_bytes32",
                "offset": 0,
                "slot": "1"
              }
            ],
            "numberOfBytes": "64"
          },
          "t_uint256": {
            "label": "uint256",
            "numberOfBytes": "32"
          },
          "t_uint8": {
            "label": "uint8",
            "numberOfBytes": "1"
          }
        }
      }
    },
    "c4f1e58fee66c52c2672c91e376fa1fe2c5beb35099654cf6b2d036a54bd1312": {
      "address": "0xE2b88fBa76909C71103E1A769377A418830147f6",
      "txHash": "0x0bbc796ad3e90f11744318b7ee5e0248cb1181607abfedb42353a5be49f3b6b5",
      "layout": {
        "solcVersion": "0.8.7",
        "storage": [
          {
            "label": "_initialized",
            "offset": 0,
            "slot": "0",
            "type": "t_uint8",
            "contract": "Initializable",
            "src": "@openzeppelin/contracts-upgradeable/proxy/utils/Initializable.sol:62",
            "retypedFrom": "bool"
          },
          {
            "label": "_initializing",
            "offset": 1,
            "slot": "0",
            "type": "t_bool",
            "contract": "Initializable",
            "src": "@openzeppelin/contracts-upgradeable/proxy/utils/Initializable.sol:67"
          },
          {
            "label": "__gap",
            "offset": 0,
            "slot": "1",
            "type": "t_array(t_uint256)50_storage",
            "contract": "ContextUpgradeable",
            "src": "@openzeppelin/contracts-upgradeable/utils/ContextUpgradeable.sol:36"
          },
          {
            "label": "__gap",
            "offset": 0,
            "slot": "51",
            "type": "t_array(t_uint256)50_storage",
            "contract": "ERC165Upgradeable",
            "src": "@openzeppelin/contracts-upgradeable/utils/introspection/ERC165Upgradeable.sol:41"
          },
          {
            "label": "_roles",
            "offset": 0,
            "slot": "101",
            "type": "t_mapping(t_bytes32,t_struct(RoleData)34_storage)",
            "contract": "AccessControlUpgradeable",
            "src": "@openzeppelin/contracts-upgradeable/access/AccessControlUpgradeable.sol:61"
          },
          {
            "label": "__gap",
            "offset": 0,
            "slot": "102",
            "type": "t_array(t_uint256)49_storage",
            "contract": "AccessControlUpgradeable",
            "src": "@openzeppelin/contracts-upgradeable/access/AccessControlUpgradeable.sol:259"
          },
          {
            "label": "TRANSFER_MANAGER_ERC721",
            "offset": 0,
            "slot": "151",
            "type": "t_address",
            "contract": "OrderValidator",
            "src": "contracts/orderValidation/OrderValidator.sol:60"
          },
          {
            "label": "TRANSFER_MANAGER_ERC1155",
            "offset": 0,
            "slot": "152",
            "type": "t_address",
            "contract": "OrderValidator",
            "src": "contracts/orderValidation/OrderValidator.sol:63"
          },
          {
            "label": "DOMAIN_SEPARATOR",
            "offset": 0,
            "slot": "153",
            "type": "t_bytes32",
            "contract": "OrderValidator",
            "src": "contracts/orderValidation/OrderValidator.sol:66"
          },
          {
            "label": "STANDARD_ROYALTY_FEE",
            "offset": 0,
            "slot": "154",
            "type": "t_uint256",
            "contract": "OrderValidator",
            "src": "contracts/orderValidation/OrderValidator.sol:69"
          },
          {
            "label": "currencyManager",
            "offset": 0,
            "slot": "155",
            "type": "t_contract(ICurrencyManager)4985",
            "contract": "OrderValidator",
            "src": "contracts/orderValidation/OrderValidator.sol:72"
          },
          {
            "label": "executionManager",
            "offset": 0,
            "slot": "156",
            "type": "t_contract(IExecutionManager)5054",
            "contract": "OrderValidator",
            "src": "contracts/orderValidation/OrderValidator.sol:75"
          },
          {
            "label": "royaltyFeeRegistry",
            "offset": 0,
            "slot": "157",
            "type": "t_contract(IRoyaltyFeeRegistry)5151",
            "contract": "OrderValidator",
            "src": "contracts/orderValidation/OrderValidator.sol:78"
          },
          {
            "label": "transferSelectorNFT",
            "offset": 0,
            "slot": "158",
            "type": "t_contract(ITransferSelectorNFTExtended)5471",
            "contract": "OrderValidator",
            "src": "contracts/orderValidation/OrderValidator.sol:81"
          },
          {
            "label": "dareMarket",
            "offset": 0,
            "slot": "159",
            "type": "t_contract(DareMarket)4786",
            "contract": "OrderValidator",
            "src": "contracts/orderValidation/OrderValidator.sol:84"
          }
        ],
        "types": {
          "t_address": {
            "label": "address",
            "numberOfBytes": "20"
          },
          "t_array(t_uint256)49_storage": {
            "label": "uint256[49]",
            "numberOfBytes": "1568"
          },
          "t_array(t_uint256)50_storage": {
            "label": "uint256[50]",
            "numberOfBytes": "1600"
          },
          "t_bool": {
            "label": "bool",
            "numberOfBytes": "1"
          },
          "t_bytes32": {
            "label": "bytes32",
            "numberOfBytes": "32"
          },
          "t_contract(DareMarket)4786": {
            "label": "contract DareMarket",
            "numberOfBytes": "20"
          },
          "t_contract(ICurrencyManager)4985": {
            "label": "contract ICurrencyManager",
            "numberOfBytes": "20"
          },
          "t_contract(IExecutionManager)5054": {
            "label": "contract IExecutionManager",
            "numberOfBytes": "20"
          },
          "t_contract(IRoyaltyFeeRegistry)5151": {
            "label": "contract IRoyaltyFeeRegistry",
            "numberOfBytes": "20"
          },
          "t_contract(ITransferSelectorNFTExtended)5471": {
            "label": "contract ITransferSelectorNFTExtended",
            "numberOfBytes": "20"
          },
          "t_mapping(t_address,t_bool)": {
            "label": "mapping(address => bool)",
            "numberOfBytes": "32"
          },
          "t_mapping(t_bytes32,t_struct(RoleData)34_storage)": {
            "label": "mapping(bytes32 => struct AccessControlUpgradeable.RoleData)",
            "numberOfBytes": "32"
          },
          "t_struct(RoleData)34_storage": {
            "label": "struct AccessControlUpgradeable.RoleData",
            "members": [
              {
                "label": "members",
                "type": "t_mapping(t_address,t_bool)",
                "offset": 0,
                "slot": "0"
              },
              {
                "label": "adminRole",
                "type": "t_bytes32",
                "offset": 0,
                "slot": "1"
              }
            ],
            "numberOfBytes": "64"
          },
          "t_uint256": {
            "label": "uint256",
            "numberOfBytes": "32"
          },
          "t_uint8": {
            "label": "uint8",
            "numberOfBytes": "1"
          }
        }
      }
    }
  }
}
